README.md
setup.cfg
setup.py
easyjaeger/__init__.py
easyjaeger.egg-info/PKG-INFO
easyjaeger.egg-info/SOURCES.txt
easyjaeger.egg-info/dependency_links.txt
easyjaeger.egg-info/not-zip-safe
easyjaeger.egg-info/requires.txt
easyjaeger.egg-info/top_level.txt
easyjaeger/helpers/__init__.py
easyjaeger/helpers/aiohttp_helpers/__init__.py
easyjaeger/helpers/aiohttp_helpers/child_middleware.py
easyjaeger/helpers/aiohttp_helpers/middleware_config.py
easyjaeger/helpers/aiohttp_helpers/parent_middleware.py
easyjaeger/tracer/__init__.py
easyjaeger/tracer/child_trace.py
easyjaeger/tracer/config.py
easyjaeger/tracer/parent_trace.py
easyjaeger/vendor/__init__.py
easyjaeger/vendor/tracer.py
tests/__init__.py