Metadata-Version: 2.1
Name: easyjaeger
Version: 0.3.0
Summary: Helper for easy breezy jaeger/zipkin in asyncio python services
Home-page: http://github.com/borisrozumnuk/cognitojwt
Author: Michail Shatalov
Author-email: misha.shatalow@gmail.com
License: MIT
Keywords: zipkin jaeger tracing aiozipkin
Platform: Any
Classifier: Development Status :: 4 - Beta
Classifier: Intended Audience :: Developers
Classifier: License :: OSI Approved :: MIT License
Classifier: Programming Language :: Python :: 3.6
Classifier: Programming Language :: Python :: 3.7
Classifier: Operating System :: OS Independent
